speclike/__init__.py
speclike/impl.py
speclike/plugin.py
speclike-0.0.2.dist-info/licenses/LICENSE
speclike-0.0.2.dist-info/METADATA
speclike-0.0.2.dist-info/WHEEL
speclike-0.0.2.dist-info/entry_points.txt
speclike-0.0.2.dist-info/top_level.txt
speclike-0.0.2.dist-info/RECORD
