Metadata-Version: 2.4
Name: speclike
Version: 0.0.2
Summary: Partial support library for structured testing
Author: minoru_jp
License: MIT License
Project-URL: Homepage, https://github.com/minoru-jp/speclike
Project-URL: Source, https://github.com/minoru-jp/speclike
Project-URL: Issues, https://github.com/minoru-jp/speclike/issues
Keywords: spec,test,marker,pytest,structured,dbc,contract,asyncio
Classifier: Programming Language :: Python :: 3
Classifier: License :: OSI Approved :: MIT License
Classifier: Development Status :: 3 - Alpha
Classifier: Intended Audience :: Developers
Classifier: Topic :: Software Development :: Libraries :: Python Modules
Requires-Python: >=3.10
License-File: LICENSE
Provides-Extra: pytest
Requires-Dist: pytest>=7.0; extra == "pytest"
Dynamic: license-file
